{
  "analysisId": "Analysis_9",
  "analysisSource": "",
  "developmentDatabase": "erspc",
  "attrition": {
    "outcomeId": [46, 46, 46, 46],
    "description": ["Original cohorts", "Initial plpData cohort or population", "First Exposure", "Removing subjects with no time at risk (if any))"],
    "targetCount": [353, 353, 353, 331],
    "uniquePeople": [353, 353, 353, 331],
    "outcomes": [234, 199, 199, 199],
    "attr_class": "data.frame",
    "attr_row.names": [1, 2, 3, 4]
  },
  "trainingTime": "1.08981108665466 secs",
  "trainingDate": "2022-10-15",
  "modelName": "logistic",
  "finalModelParameters": {
    "variance": 6.9947,
    "log_likelihood": -138.8186
  },
  "hyperParamSearch": [0.5464, 0.6155, 0.743],
  "developmentDatabaseId": "erspc"
}
